{
    "type":"FeatureCollection",    
    "features":[
        {
            "type":"building",
            "id":"Regions.0",
            "geometry":{
                "type":"MultiPolygon",
                "coordinates":[
                    [
                        [
                            [
                                12811287.444080088,
                                3531809.1198588004
                            ],
                            [
                                12811085.2044306,
                                3531602.1029314934
                            ],
                            [
                                12811277.889451552,
                                3531426.934717375
                            ],
                            [
                                12811662.463250112,
                                3531503.37174566
                            ],
                            [
                                12811287.444080088,
                                3531809.1198588004
                            ]
                        ]
                    ]
                ]
            }
        }
    ]
}